README
setup.py
django_locking.egg-info/PKG-INFO
django_locking.egg-info/SOURCES.txt
django_locking.egg-info/dependency_links.txt
django_locking.egg-info/requires.txt
django_locking.egg-info/top_level.txt
locking/__init__.py
locking/admin.py
locking/decorators.py
locking/models.py
locking/urls.py
locking/utils.py
locking/views.py
locking/tests/__init__.py
locking/tests/admin.py
locking/tests/models.py
locking/tests/tests.py
locking/tests/urls.py
locking/tests/utils.py