Metadata-Version: 1.0
Name: django-locking
Version: 0.2.1
Summary: Prevents users from doing concurrent editing in Django. Works out of the box in the admin interface, or you can integrate it with your own apps using a public API.
Home-page: http://stdbrouw.github.com/django-locking/
Author: Stijn Debrouwere
Author-email: UNKNOWN
License: BSD
Download-URL: http://www.github.com/stdbrouw/django-locking/tarball/master
Keywords: locking mutex
Platform: UNKNOWN
Classifier: Development Status :: 4 - Beta
Classifier: Environment :: Web Environment
Classifier: Framework :: Django
Classifier: Intended Audience :: Developers
Classifier: License :: OSI Approved :: BSD License
Classifier: Operating System :: OS Independent
Classifier: Programming Language :: Python
Classifier: Topic :: Software Development :: Libraries :: Python Modules
Classifier: Topic :: Utilities
